{
    "intents": [
        {
            "tag": "greeting",
            "patterns": ["Hi there", "How are you", "Is anyone there?", "Hey", "Hola", "Hello", "Good day", "What's up?", "Howdy", "Greetings"],
            "responses": ["Hello", "Good to see you again", "Hi there, how can I help?", "Hello! How can I assist you today?"],
            "context": [""]
        },
        {
            "tag": "goodbye",
            "patterns": ["Bye", "See you later", "Goodbye", "Nice chatting to you, bye", "Till next time", "Take care", "Catch you later", "Farewell"],
            "responses": ["See you!", "Have a nice day", "Bye! Come back again soon.", "Goodbye! Have a great day!"],
            "context": [""]
        },
        {
            "tag": "thanks",
            "patterns": ["Thanks", "Thank you", "That's helpful", "Awesome, thanks", "Thanks for helping me", "I appreciate it", "Much obliged", "Thanks a lot"],
            "responses": ["My pleasure", "You're Welcome", "Happy to help!", "Anytime!"],
            "context": [""]
        },
        {
            "tag": "courses",
            "patterns": ["What courses do you offer?",
                        "Tell me about the available courses",
                        "What subjects can I study?",
                        "List the courses available",
                        "What are the popular courses?"
                    ],
            "responses": ["We offer courses in Data Science, AI, Machine Learning, Python Full Stack, Flutter App Development, and more.",
                        "Our courses include topics like Data Science, AI, Machine Learning, Python Full Stack, Flutter App Development, and many more.",
                        "You can study subjects such as Data Science, Python Full Stack, Flutter App Development, Digital Marketing, and UI/UX Design, etc.",
                        "Codeme Hub offers a variety of courses including Data Science, Python Full Stack, Flutter App Development, Digital Marketing, and UI/UX Design."
                    ],
            "context": [""]
        },
        {
            "tag": "pricing",
            "patterns": ["How much do the courses cost?",
                        "Tell me about the pricing", "What are the course fees?",
                        "Are there any discounts?", "What is the price of the courses?"
                    ],
            "responses": ["The course fees vary depending on the program. Please visit our website [codemehub.com](https://codemehub.com/) for detailed pricing information.", 
                        "Our pricing details are available on the website. Check out our website [codemehub.com](https://codemehub.com/).",
                        "You can find the pricing information for each course on our website [codemehub.com](https://codemehub.com/)."
                    ],
            "context": [""]
        },
        {
            "tag": "enrollment",
            "patterns": ["How do I enroll?",
                        "What is the enrollment process?",
                        "How can I sign up?", "What are the steps to enroll?", "How to register for a course?"
                    ],
            "responses": ["For enrollment, simply visit our website [codemehub.com](https://codemehub.com/). If you need any help with the process, feel free to reach out to our support team at 8086 7401 11.",
                        "To join a course, head over to our website [codemehub.com](https://codemehub.com/). Our support team is also available to assist you with enrollment at 8086 7401 11.",
                        "You can enroll in a course by visiting our website [codemehub.com](https://codemehub.com/). For any assistance during the enrollment process, please contact our support team at 8086 7401 11.",
                        "Visit [codemehub.com](https://codemehub.com/) to enroll in a course. If you require help, our support team is ready to assist you at 8086 7401 11.",
                        "Enrollment is easy via our website [codemehub.com](https://codemehub.com/). Should you need any assistance, don't hesitate to call our support team at 8086 7401 11."
                    ],
            "context": [""]
        },
        {  
            "tag":"duration",
            "patterns":["What is the duration of each course? ",
                        "How long does each course last?",
                        "What is the length of each course?",
                        "Can you tell me the duration of each course?",
                        "How much time does each course take to complete?",
                        "What are the course durations?",
                        "How many hours is each course?",
                        "How long is each course?",
                        "How many weeks does each course run?",
                        "How long does it take to complete each course?"
                    ],
            "responses":["The duration of each course varies depending on the subject. For specific details on course duration, please visit our website at [codemehub.com](https://codemehub.com/) or contact our support team at 8086 7401 11.",
                        "Course durations differ based on the subject matter. For detailed information on each course, please visit our website at [codemehub.com](https://codemehub.com/) or reach out to our support team at 8086 7401 11.",
                        "The length of each course can vary depending on the topic. To find out more about the duration of specific courses, please check our website [codemehub.com](https://codemehub.com/) or contact our support team at 8086 7401 11."
                    ],
             "context": [""]
        },
        {
            "tag": "support",
            "patterns": ["How can I get support?",
                        "What is the customer support contact?",
                        "I need help", "How do I reach support?",
                        "Who can assist me?"
                    ],
            "responses": ["For support, you can contact our customer service at [codemehub.com](https://codemehub.com/)  or call us at 8086 7401 11.",
                        "Reach out to our support team via email at [codemehub.com](https://codemehub.com/) or call our helpline at 8086 7401 11.",
                        "You can get assistance by emailing [codemehub.com](https://codemehub.com/) or by calling 8086 7401 11."
                    ],
            "context": [""]
        },
        {
            "tag":"placement_support",
            "patterns":["Can you tell me about the placement support offered by Codeme Hub?",
                        "What types of placement services does Codeme Hub offer?",
                        "How does Codeme Hub help with job placements after course completion?",
                        "What kind of career assistance can I expect from Codeme Hub?",
                        "Does Codeme Hub provide any placement help or job support?",
                        "Could you explain the placement assistance provided by Codeme Hub?",
                        "How does Codeme Hub support students in finding jobs?",
                        "What job placement assistance does Codeme Hub offer its students?",
                        "What are the placement opportunities provided by Codeme Hub?"
                     ],
            "responses":["Codeme Hub guarantees complete placement support. Our committed placement team assists students with crafting their resumes, preparing for interviews, and connecting them with leading IT companies.",
                        "At Codeme Hub, we offer comprehensive placement assistance. Our specialized placement team helps students build their resumes, get ready for interviews, and establish connections with top-tier IT firms.",
                       "We at Codeme Hub ensure 100% placement support. Our dedicated team aids students in resume creation, interview preparation, and networking with prominent IT companies."
                    ],
            "context":[""]          

        },
        {
            "tag":"real_time_training",
            "patterns":["Does the training include live projects and real-time sessions?",
                        "Are live projects part of the real-time training provided?",
                        "Is the training conducted in real-time, and does it involve live projects?",
                        "Do you offer real-time training sessions with practical live projects?",
                        "Will I get to work on live projects during the real-time training?"],
            "responses":["Yes, at Codeme Hub, we integrate live projects into our real-time training, allowing students to gain valuable practical knowledge and experience.",
                        "Indeed, Codeme Hub offers training in real-time and includes live projects as part of the curriculum. This helps students develop practical skills and hands-on expertise in their field.",
                        "Certainly, Codeme Hub's training program includes real-time sessions and live projects, which are essential for students to gain hands-on experience and practical insights.",
                        "Yes, Codeme Hub ensures that students receive real-time training alongside live projects, providing them with practical knowledge and experience in their chosen domain."],
            "context":[""]           
        },
        {
            "tag":"location",
            "patterns":["What is the location of Codeme Hub?",
                        "Can you tell me the address of Codeme Hub?",
                        "Where are the Codeme Hub offices situated?",
                        "Could you provide the location details for Codeme Hub?",
                        "Where is Codeme Hub based?","Where is the headquarters of Codeme Hub?",
                        "In which city is Codeme Hub located?"],
            "responses":["Codeme Hub, one of Kerala's leading software training institutions, is based in Calicut. For detailed location information, visit our website at [codemehub.com](https://codemehub.com/) or reach out to us at 8086 7401 11.",
                       "Located in Calicut, Codeme Hub is a premier software training institution in Kerala. For more specific details about our location, please check our website [codemehub.com](https://codemehub.com/) or give us a call at 8086 7401 11.",
                       "Codeme Hub, a top software training center in Kerala, can be found in Calicut. For exact location details, please visit [codemehub.com](https://codemehub.com/) or contact us at 8086 7401 11."
                    ],
            "context":[""]           
        },
        {
            "tag":"course_information_online",
            "patterns": [
                    "Can I get more information about the courses online?",
                    "Is there more information about the courses available online?",
                    "Where can I find more details about the courses?",
                    "How can I get more information about the courses?",
                    "Can you tell me more about the courses online?",
                    "Where can I find more information on your courses?"
                ],
            "responses": [
                    "Sure! You can find more information about our courses on our website codemehub.com.",
                    "Visit our website codemehub.com to get detailed information about the courses we offer.",
                    "For more details about the courses, please go to codemehub.com.",
                    "You can learn more about our courses by visiting our website at codemehub.com."
                ],
            "context":[""]
    
        },
        {
            "tag": "course_access_modes",
            "patterns": [
                    "Can I access the course offline?",
                    "Is there an offline mode for the course?",
                    "Can I download the course for offline use?",
                    "Is the course available offline?",
                    "Can I study the course without an internet connection?",
                    "Can I access the course offline?",
                    "Is the course available offline?",
                    "Do you offer offline mode for the course?",
                    "Can I download the course content for offline access?",
                    "Is offline access available for the course?"
                
                ],
            "responses": [
                    "Codeme offers both online and offline modes. You can download our application on your device and enjoy all the benefits in real-time.",
                    "Yes, you can access the course offline by downloading our app on your device. This way, you can enjoy all the course benefits in real-time, even without an internet connection.",
                    "Our courses are available in both online and offline modes. Simply download our application to your device to access the course content offline and enjoy real-time benefits.",
                    "You can indeed access the course offline. Download our application on your device to benefit from the course in real-time, even without an internet connection.",
                    "Codeme provides the option to download the application to your device for offline access. This allows you to enjoy the course benefits in real-time without needing an internet connection."
                ],
            "context": [""]


        },
        {
            "tag": "course_prerequisites",
            "patterns": [
                    "Are there any prerequisites for enrolling in certain courses?",
                    "Do I need to have any prerequisites for some courses?",
                    "Are there specific requirements for enrolling in certain courses?",
                    "Do some courses have specific prerequisites for enrollment?",
                    "Are there required qualifications or prior knowledge needed for certain courses?",
                    "Is there any prior coursework or experience needed for certain courses?",
                    "Are certain courses restricted to students with specific prerequisites?",
                    "What are the necessary prerequisites for enrolling in certain programs?",
                    "Do any courses have mandatory prerequisites that need to be completed first?",
                    "Are there any enrollment requirements or prerequisites for particular courses?"
                ],
            "responses": [
                    "Some courses may have prerequisites, such as prior knowledge of specific concepts or skills. You can find information about course prerequisites in the course description before enrolling [codemehub.com](https://codemehub.com/).",
                    "Certain courses may require prerequisites, like prior knowledge or skills. Please refer to the course description for details on specific requirements [codemehub.com](https://codemehub.com/).",
                    "Yes, some courses have prerequisites. Details about these requirements can be found in the course descriptions available before enrolling [codemehub.com](https://codemehub.com/)."
                    ],
            "context":[""]
        },
        {
            "tag": "course_change_refund",
            "patterns": [
                    "Can I switch courses or get a refund if I'm not satisfied with my current course?",
                    "Am I able to change courses or receive a refund if I'm unhappy with my current course?",
                    "What is the policy for switching courses or getting a refund if I'm dissatisfied with my current course?",
                    "Is it possible to transfer to a different course or receive a refund if I'm unhappy with my current one?",
                    "What are the options for switching courses or getting a refund if the current course doesn't meet my expectations?",
                    "Can I change to another course or get my money back if I'm dissatisfied with the current course?",
                    "If I'm not satisfied with my current course, can I enroll in a different one or request a refund?",
                    "Are there provisions for switching courses or obtaining a refund if the current course is unsatisfactory?",
                    "Can I opt for another course or get a refund if the one I'm taking doesn't suit me?"
                    ],
            "responses": [
                    "We strive to ensure your satisfaction with our courses. If you're not satisfied with your current course, please reach out to our customer support team for assistance. We may be able to offer course transfers or refunds on a case-by-case basis.",
                    "Your satisfaction is important to us. If you're unhappy with your current course, please contact our customer support team. We can discuss options for course changes or refunds based on your situation.",
                    "If you're not satisfied with your current course, please contact our customer support team. We evaluate requests for course transfers or refunds on a case-by-case basis to ensure your needs are met."
                ],
            "context":[""]

        },
        {
            "tag": "course_certification",
            "patterns": [
                    "Does Codeme offer certification upon completion of courses?",
                    "Are there certificates awarded after completing the courses?",
                    "Do I get a certificate when I finish the course?",
                    "Is there a certification for completing the course?",
                    "What kind of certification do you offer after finishing the course?"
                ],
            "responses": [
                    "Yes, Codeme offers certification upon completion of courses. Our certificates are recognized in the industry and can help you showcase your skills and expertise to potential employers.",
                    "Upon completing our courses, you will receive a certification from Codeme. These certificates are valuable in demonstrating your proficiency in the subject matter.",
                    "Codeme provides certification upon successful completion of our courses. These certificates are widely accepted and can enhance your career prospects.",
                    "After finishing the course, you will receive a certificate from Codeme. This certification validates your achievement and proficiency in the course material.",
                    "Upon completing our courses, you will receive a certification that verifies your skills and knowledge in the respective field. These certificates are highly regarded by employers."
                ],
    "context": [""]
        },
        {
            "tag": "data_science_definition",
            "patterns": [
                    "What is Data Science?",
                    "Can you explain Data Science?",
                    "I want to learn more about Data Science"
                ],
            "responses": [
                    "Data science is a field that combines various tools, techniques, and knowledge from statistics, computer science, and domain expertise to extract meaningful insights and knowledge from data. In simpler terms, it's about turning raw data into useful information that can help people and organizations make better decisions.",
                    "Data science involves analyzing large volumes of data to uncover hidden patterns, correlations, and insights that organizations use to improve decision-making and solve complex problems.",
                    "Data science is the process of using data to understand trends, behaviors, and relationships, helping businesses and researchers make informed choices and predictions.",
                    "Data science involves analyzing data to uncover patterns, solve problems, and make decisions based on insights derived from large datasets."
                ],
            "context":[""]        

        },
        {
            "tag":"data_science_key_components",
            "patterns":[
                "What does the Data Science course include?",
                "Can you tell me about the contents of the Data Science course?",
                "What will I learn in the Data Science course?",
                "What topics are covered in the Data Science course?",
                "What's included in the Data Science course?",
                "Can you outline the main components involved in Data Science?",
                "What are the foundational pillars of Data Science?",
                "Could you describe the core parts of Data Science?",
                "What are the primary components that make up Data Science?",
                "What are the key elements in the field of Data Science?",
                "What are the major components of a Data Science workflow?",
                "Can you explain the fundamental components of Data Science?"
                 ],
            "responses":[
                "Data Science has several key components:Data Collection,Data Cleaning,Data Analysis,Data Visualization,Statistics,Machine Learning.Learn more on our [Data Science](https://codemehub.com/data-science-course-in-calicut-kerala/).",
                "The main components of Data Science are Data Collection, Data Cleaning, Data Analysis, Data Visualization, Statistics, and Machine Learning. These components enable professionals to gather, prepare, analyze, and present data effectively, facilitating informed decision-making across various domains. Check out the full syllabus on our [Data Science page](https://codemehub.com/data-science-course-in-calicut-kerala/).",
                "Data Science encompasses several essential components: Data Collection, Data Cleaning, Data Analysis, Data Visualization, Statistics, and Machine Learning. Each plays a crucial role in transforming raw data into valuable insights for decision-making.For more detailed information, visit our [Data Science page](https://codemehub.com/data-science-course-in-calicut-kerala/).",
                "The Data Science course includes several key components such as Data Collection, Data Cleaning, Data Analysis, Data Visualization, Statistics, and Machine Learning. For more detailed information, visit our [Data Science page](https://codemehub.com/data-science-course-in-calicut-kerala/).",
                "Our Data Science course covers Data Collection, Data Cleaning, Data Analysis, Data Visualization, Statistics, and Machine Learning. Check out the full syllabus on our [Data Science page](https://codemehub.com/data-science-course-in-calicut-kerala/).",
                "In the Data Science course, you will learn about Data Collection, Data Cleaning, Data Analysis, Data Visualization, Statistics, and Machine Learning. For further details, please visit our [Data Science page](https://codemehub.com/data-science-course-in-calicut-kerala/).",
                "The Data Science course comprehensively covers Data Collection, Data Cleaning, Data Analysis, Data Visualization, Statistics, and Machine Learning. Learn more on our [Data Science page](https://codemehub.com/data-science-course-in-calicut-kerala/)."
 
                ],
            "context":[""]
        },
        {
            "tag":"data_collection",
            "patterns":[
                    "Could you explain the concept of data collection?"
                    ,"What does data collection involve?"
                    ,"How would you define data collection?"
                    ,"Can you describe the process of data collection?"
                    ,"What are the key aspects of data collection?"
                    ,"In simple terms, what is meant by data collection?"
                ],
            "responses":[
                "Data collection refers to the process of gathering raw information and facts from various sources to be used for analysis, decision-making, or research purposes.",
                "Data collection is the systematic process of gathering and measuring information on variables of interest, typically in a structured and organized manner.",
                "Data collection is the act of gathering data points or information from different sources, which can include surveys, observations, or automated systems. It is essential for building datasets used in analysis and decision-making."
                ],
            "context":[""]
        },
        {
            "tag": "data_cleaning",
            "patterns": [
                "What is data cleaning?",
                "Can you explain data cleaning?",
                "What does data cleaning involve?"
                ],
            "responses": [
                "Data cleaning is a crucial step in data preprocessing that involves identifying and correcting errors or inconsistencies in the dataset.",
                "Data cleaning ensures that the data is accurate, complete, and properly formatted for analysis.",
                "In simpler terms, data cleaning is about preparing data so that it's reliable and suitable for further analysis and modeling."
                ],
            "context": [""]

        },
        {
            "tag": "data_visualization",
            "patterns": [
                "What is data visualization?",
                "Can you explain data visualization?",
                "What does data visualization involve?"
                ],
            "responses": [
                "Data visualization is the representation of data in graphical or pictorial format to help uncover patterns, trends, and insights.",
                "It involves creating visual representations like charts, graphs, and maps to make complex data more understandable and accessible.",
                "In simpler terms, data visualization is about using visuals to communicate information and insights from data effectively."
                ],
            "context": [""]
        },
        {
            "tag": "data_analysis",
            "patterns": [
                "What is data analysis?",
                "Can you explain data analysis?",
                "How does data analysis work?",
                "What does the Data Analysis course include?",
                "Tell me about the Data Analysis course.",
                "What will I learn in the Data Analysis course?",
                "Can you explain the Data Analysis course?",
                "What topics are covered in the Data Analysis course?"
                ],
            "responses": [
                "Data analysis is the systematic examination of data, often with the goal of discovering meaningful patterns and insights that inform decision-making or research.Check out the full syllabus on our [Data analysis page](https://codemehub.com/best-data-analytics-course-in-calicut-kerala/).",
                "Data analysis is the process of inspecting, cleansing, transforming, and modeling data with the goal of discovering useful information, informing conclusions, and supporting decision-making.For further details, please visit our [Data analysis page](https://codemehub.com/best-data-analytics-course-in-calicut-kerala/).",
                "The Data Analysis course includes key topics such as data collection, data cleaning, data visualization, statistical analysis, and using tools like Excel, SQL, and Python. You'll learn how to extract meaningful insights from data and make data-driven decisions.Check out the full syllabus on our [Data analysis page](https://codemehub.com/best-data-analytics-course-in-calicut-kerala/).",
                "In the Data Analysis course, you'll cover essential areas like data collection methods, cleaning and preparing data, visualizing data with charts and graphs, and performing statistical analysis using tools like Excel, SQL, and Python.Learn more on our [Data analysis page](https://codemehub.com/best-data-analytics-course-in-calicut-kerala/).",
                "Our Data Analysis course covers everything from collecting and cleaning data to visualizing and analyzing it using statistical methods. You'll also get hands-on experience with tools like Excel, SQL, and Python.Check out the full syllabus on our [Data analysis page](https://codemehub.com/best-data-analytics-course-in-calicut-kerala/).",
                "The Data Analysis course provides comprehensive training on data collection, cleaning, visualization, and statistical analysis. You'll learn to use tools like Excel, SQL, and Python to analyze data and draw meaningful conclusions.For further details, please visit our [Data analysis page](https://codemehub.com/best-data-analytics-course-in-calicut-kerala/).",
                "Topics covered in the Data Analysis course include data collection, data cleaning, data visualization, statistical analysis, and proficiency with tools like Excel, SQL, and Python. This course will help you turn raw data into actionable insights.Learn more on our [Data analysis page](https://codemehub.com/best-data-analytics-course-in-calicut-kerala/)."
        
                ],
            "context": [""]
        },
        {
            "tag": "statistics",
            "patterns": [
                "What are statistics?",
                "Can you explain statistics?",
                "Tell me about statistics"
                ],
            "responses": [
                "Statistics is a branch of mathematics that involves collecting, analyzing, interpreting, presenting, and organizing data. It encompasses methods for summarizing data, drawing conclusions from it, and making informed decisions based on probabilities and trends.",
                "Statistics is the discipline that involves collecting, analyzing, interpreting, presenting, and organizing data.",
                "It includes methods for summarizing data, drawing conclusions from it, and making decisions based on data analysis.",
                "Statistics plays a crucial role in various fields such as business, economics, science, and social sciences by providing insights and making predictions.",
                "Statistics is the science of collecting, analyzing, and interpreting numerical data to understand patterns, trends, and relationships in the real world"
                ],
            "context": [""]

        },
        {
            "tag": "machine_learning",
            "patterns": [
                "What is machine learning?",
                "Can you explain machine learning?",
                "Tell me about machine learning"
                ],
            "responses": [
                "Machine learning is a branch of artificial intelligence (AI) that involves developing algorithms and statistical models that allow computer systems to learn from and make decisions or predictions based on data, without explicit programming.",
                "Machine learning is a subset of artificial intelligence that involves building algorithms and statistical models to enable computers to learn from and make predictions or decisions based on data.",
                "Machine learning is a type of artificial intelligence where computers learn from data and improve their ability to perform tasks without being explicitly programmed.",
                "Machine learning algorithms analyze data to identify patterns and make decisions, enabling applications such as speech recognition, image classification, and recommendation systems."
                ],
            "context": [""]
        },
        {
            "tag": "flutter_app_development_course",
            "patterns": [
                "What can I expect from the Flutter App Development course?",
                "What does the Flutter App Development course cover?",
                "What will I learn in the Flutter App Development course?",
                "Can you tell me about the Flutter App Development course?"
               ],
            "responses": [
                "The Flutter App Development course covers everything from the basics to advanced concepts of Flutter. You'll learn to build beautiful, natively compiled applications for mobile, web, and desktop from a single codebase. For more details, visit our [Flutter App Development Page](https://codemehub.com/flutter-training-in-calicut-kerala/).",
                "In the Flutter App Development course, you can expect to learn how to create responsive and attractive user interfaces, handle user input, and connect your app to a backend. Check out our [Flutter App Development Page](https://codemehub.com/flutter-training-in-calicut-kerala/) for more information.",
                "Our Flutter App Development course will guide you through the process of building high-performance apps. You'll get hands-on experience with real projects, learning best practices in Flutter development. Find out more on our [Flutter App Development Page](https://codemehub.com/flutter-training-in-calicut-kerala/).",
                "This course provides a comprehensive introduction to Flutter, covering topics such as state management, navigation, and integrating APIs. Visit our [Flutter App Development Page](https://codemehub.com/flutter-training-in-calicut-kerala/) to learn more."
               ],
            "context": [""]
        },
        {
            "tag": "full_stack_python_course_includes",
            "patterns": [
                "What does the Full Stack Python course include?",
                "Can you tell me about the Full Stack Python course?",
                "What's covered in the Full Stack Python course?",
                "What topics are included in the Full Stack Python course?",
                "What will I learn in the Full Stack Python course?"
                ],
            "responses": [
                "The Full Stack Python course includes comprehensive coverage of both front-end and back-end development. You'll learn HTML, CSS, JavaScript, and popular frameworks like React or Angular for front-end development. For the back-end, you'll dive into Python, Django or Flask, RESTful API development, and database management with SQL and NoSQL databases .For more details, visit our [Full Stack Python Page](https://codemehub.com/python-full-stack-developer-training-in-calicut/).",
                "Our Full Stack Python course covers a wide range of topics including front-end technologies like HTML, CSS, and JavaScript, as well as back-end technologies such as Python, Django, Flask, and database management. You'll also work on hands-on projects to build full stack applications. Find out more on our [Full Stack Python Page](https://codemehub.com/python-full-stack-developer-training-in-calicut/).",
                "In the Full Stack Python course, you'll learn how to create complete web applications from scratch. This includes front-end development with HTML, CSS, JavaScript, and frameworks like React or Angular, and back-end development using Python, Django, Flask, and databases.For more details, visit our [Full Stack Python Page](https://codemehub.com/python-full-stack-developer-training-in-calicut/).",
                "The Full Stack Python course encompasses both client-side and server-side programming. Topics include HTML, CSS, JavaScript, React or Angular for front-end, and Python, Django, Flask, and database integration for back-end.Check out our [Full Stack Python Page](https://codemehub.com/python-full-stack-developer-training-in-calicut/) for more information.",
                "You'll get to learn a full range of technologies in the Full Stack Python course, starting from front-end languages like HTML, CSS, and JavaScript, moving on to frameworks like React or Angular, and covering back-end development with Python, Django, Flask, and databases.Check out our [Full Stack Python Page](https://codemehub.com/python-full-stack-developer-training-in-calicut/) for more information."
               ],
            "context": [""]
        },
        {
            "tag": "business_analysis_course_components",
            "patterns": [
                "What are the key components of the Business Analysis course?",
                "Can you tell me about the Business Analysis course components?",
                "What topics are covered in the Business Analysis course?",
                "What will I learn in the Business Analysis course?"
               ],
            "responses": [
                "The Business Analysis course covers essential components such as requirements gathering, stakeholder analysis, process modeling, data analysis, and solution evaluation. It also includes practical skills like communication, documentation, and software tools used in business analysis.",
                "In the Business Analysis course, you'll explore key areas including requirements management, stakeholder engagement, business process modeling, data analysis techniques, and evaluation of business solutions. Practical tools and techniques are also emphasized.",
                "Key components of the Business Analysis course include requirements elicitation, stakeholder management, business process modeling, data analysis for decision-making, and evaluating solutions against business objectives. Practical applications and industry tools are integrated throughout the course.",
                "You'll delve into critical aspects of business analysis in the course, covering requirements management, stakeholder communication, process modeling, data analysis methods, and solution evaluation based on business needs. Practical exercises and tools are incorporated."
               ],
            "context": [""]

        },
        {
            "tag": "business_analysis_course_audience",
            "patterns": [
                "Who should take the Business Analysis course?",
                "Who is the Business Analysis course for?",
                "Who can benefit from the Business Analysis course?"
              ],
            "responses": [
                "This course is designed for aspiring business analysts, project managers, and professionals seeking to enhance their analytical skills for making informed business decisions.",
                "The Business Analysis course is suitable for individuals looking to become proficient in analyzing business requirements, managing stakeholders, and improving business processes.",
                "Professionals aiming to develop expertise in business analysis, including requirements gathering, process modeling, and data analysis, will find this course beneficial."
            ],
            "context": [""]
        },
        {
            "tag": "digital_marketing_course",
            "patterns": [
                "What topics are included in the Digital Marketing course?",
                "Can you tell me about the Digital Marketing course?",
                "What will I learn in the Digital Marketing course?",
                "What does the Digital Marketing course cover?",
                "What is taught in the Digital Marketing course?"
        ],
           "responses": [
                "The Digital Marketing course covers a wide range of topics, including SEO, social media marketing, email marketing, content marketing, and pay-per-click advertising. You'll learn strategies to effectively promote brands and products online. For more details, visit [Digital Marketing course](https://codemehub.com/digital-marketing-institute-in-calicut-kerala/).",
                "In the Digital Marketing course, you'll learn about SEO, social media marketing, email marketing, content marketing, and pay-per-click advertising. These topics will help you develop effective online marketing strategies. For more information, please check [Digital Marketing course](https://codemehub.com/digital-marketing-institute-in-calicut-kerala/).",
                "Our Digital Marketing course includes essential topics such as SEO, social media marketing, email marketing, content marketing, and pay-per-click advertising. You'll gain the skills needed to promote brands and products online. For more details, visit [Digital Marketing course](https://codemehub.com/digital-marketing-institute-in-calicut-kerala/).",
                "The Digital Marketing course teaches you about SEO, social media marketing, email marketing, content marketing, and pay-per-click advertising. You'll learn how to create and implement effective online marketing strategies. More details can be found on [Digital Marketing course](https://codemehub.com/digital-marketing-institute-in-calicut-kerala/).",
                "Topics covered in the Digital Marketing course include SEO, social media marketing, email marketing, content marketing, and pay-per-click advertising. These areas will equip you with the skills to promote brands and products effectively online. For more information, visit [Digital Marketing course](https://codemehub.com/digital-marketing-institute-in-calicut-kerala/)."
            ],
            "context": [""]
        },
        {
            "tag": "ui_ux_design_course",
            "patterns": [
                "What skills will I acquire in the UI/UX Design course?",
                "Can you tell me what I'll learn in the UI/UX Design course?",
                "What does the UI/UX Design course cover?",
                "What will I learn in the UI/UX Design course?",
                "What are the key takeaways from the UI/UX Design course?"
            ],
            "responses": [
                "The UI/UX Design course teaches you the principles of user interface and user experience design. You'll learn to create intuitive and visually appealing interfaces, conduct user research, create wireframes and prototypes, and test designs for usability. You can find more details on our website at [UI/UX Design course](https://codemehub.com/ui-ux-design-course-in-calicut-kerala/).",
                "In the UI/UX Design course, you'll acquire skills in designing intuitive and attractive user interfaces, conducting thorough user research, creating wireframes and prototypes, and testing designs to ensure usability. For more information, visit [UI/UX Design course](https://codemehub.com/ui-ux-design-course-in-calicut-kerala/).",
                "The UI/UX Design course covers the essentials of user interface and user experience design. You'll learn to design user-friendly and visually appealing interfaces, perform user research, develop wireframes and prototypes, and conduct usability testing. Explore more on our website at [Course Website URL](https://codemehub.com/ui-ux-design-course-in-calicut-kerala/).",
                "You'll learn essential skills in the UI/UX Design course, including creating intuitive interfaces, performing user research, designing wireframes and prototypes, and testing for usability. Check out our website for detailed information: [UI/UX Design course](https://codemehub.com/ui-ux-design-course-in-calicut-kerala/).",
                "The UI/UX Design course provides skills in user interface and user experience design, including designing intuitive and appealing interfaces, conducting user research, creating wireframes and prototypes, and usability testing. Visit our website at [UI/UX Design course](https://codemehub.com/ui-ux-design-course-in-calicut-kerala/) for more details."
            ],
            "context": [""]
        },
        {
            "tag": "data_science_course_duration",
            "patterns": [
                "How long is the Data Science course at Codeme Hub?",
                "What is the duration of the Data Science course at Codeme Hub?",
                "How much time does the Data Science course at Codeme Hub take?",
                "Duration of Data Science course at Codeme Hub?",
                "How long does the Data Science course at Codeme Hub take?",
                "What is the duration of the Data Science course at Codeme Hub?",
                "Can you tell me how many months the Data Science course at Codeme Hub lasts?",
                "How much time is required to complete the Data Science course at Codeme Hub?"
        
            ],
            "responses": [
                "The Data Science course at Codeme Hub typically lasts for 7 months, including live projects and practical assignments.Find out more on our [Data Science page](https://codemehub.com/data-science-course-in-calicut-kerala/).",
                "At Codeme Hub, the Data Science course is designed to span approximately 7 months, allowing for comprehensive learning and hands-on experience.For further details, please visit our [Data Science page](https://codemehub.com/data-science-course-in-calicut-kerala/).",
                "You can expect the Data Science course at Codeme Hub to run for about 7 months, during which you will engage in live projects and practical exercises.For further details, please visit our [Data Science page](https://codemehub.com/data-science-course-in-calicut-kerala/).",
                "The duration of the Data Science course at Codeme Hub is usually around 7 months, incorporating hands-on projects and real-world applications.Find out more on our [Data Science page](https://codemehub.com/data-science-course-in-calicut-kerala/).",
                "Codeme Hub offers a Data Science course that typically extends over a period of 7 months, focusing on practical learning and live project experiences.For further details, please visit our [Data Science page](https://codemehub.com/data-science-course-in-calicut-kerala/)."
            ],
            "context": [""]

        },
        {
            "tag": "python_full_stack_course_duration",
            "patterns": [
                "What is the duration of the Python Full Stack course?",
                "How long does the Python Full Stack course take?",
                "Duration of Python Full Stack course?",
                "How much time is required for the Python Full Stack course?",
                "Can you tell me the duration of the Python Full Stack course?",
                "What is the timeframe for completing the Python Full Stack course?",
                "How many months does the Python Full Stack course span?",
                "What is the length of the Python Full Stack course?"
   
            ],
            "responses": [
                "The Python Full Stack course is designed to be completed in 6 months, encompassing both front-end and back-end development.Check out our [Full Stack Python Page](https://codemehub.com/python-full-stack-developer-training-in-calicut/) for more information. ",
                "At Codeme Hub, the Python Full Stack course typically spans over a period of 6 months, covering both front-end and back-end development.Find out more on our [Full Stack Python Page](https://codemehub.com/python-full-stack-developer-training-in-calicut/).",
                "You can expect the Python Full Stack course at Codeme Hub to last approximately 6 months, focusing on comprehensive training in front-end and back-end development.Find out more on our [Full Stack Python Page](https://codemehub.com/python-full-stack-developer-training-in-calicut/).",
                "The duration of the Python Full Stack course at Codeme Hub is usually around 6 months, offering extensive learning opportunities in both front-end and back-end development.Check out our [Full Stack Python Page](https://codemehub.com/python-full-stack-developer-training-in-calicut/) for more information.",
                "Codeme Hub offers a Python Full Stack course that is structured to be completed in 6 months, providing in-depth knowledge and skills in front-end and back-end development.Find out more on our [Full Stack Python Page](https://codemehub.com/python-full-stack-developer-training-in-calicut/)."
            ],
            "context": [""]
        },
        {
            "tag": "flutter_app_dev_course_duration",
            "patterns": [
                "How long does it take to complete the Flutter App Development course?",
                "Duration of Flutter App Development course?",
                "What is the timeframe for Flutter App Development course?",
                "How much time is required for Flutter App Development course?",
                "How long does the Flutter App Development course take?",
                "Can you tell me the duration of the Flutter App Development course?",
                "What is the timeframe for completing the Flutter App Development course?",
                "How many months does the Flutter App Development course span?",
                "What is the length of the Flutter App Development course?"
        
            ],
            "responses": [
                "The Flutter App Development course usually spans 4 months, covering the essential concepts and hands-on projects.Visit our [Flutter App Development Page](https://codemehub.com/flutter-training-in-calicut-kerala/) to learn more.",
                "At Codeme Hub, the Flutter App Development course typically takes around 4 months to complete, focusing on essential concepts and practical projects. Find out more on our [Flutter App Development Page](https://codemehub.com/flutter-training-in-calicut-kerala/).",
                "You can expect the Flutter App Development course at Codeme Hub to last approximately 4 months, providing comprehensive training in Flutter and hands-on project experience. Find out more on our [Flutter App Development Page](https://codemehub.com/flutter-training-in-calicut-kerala/).",
                "The duration of the Flutter App Development course at Codeme Hub is generally about 4 months, offering in-depth learning in Flutter development and practical application.Visit our [Flutter App Development Page](https://codemehub.com/flutter-training-in-calicut-kerala/) to learn more.",
                "Codeme Hub offers a Flutter App Development course designed to be completed in 4 months, emphasizing both theoretical understanding and practical implementation. Find out more on our [Flutter App Development Page](https://codemehub.com/flutter-training-in-calicut-kerala/)."
            ],
            "context": [""]
        },
        {
            "tag": "digital_marketing_course_duration",
            "patterns": [
                "What is the duration of the Digital Marketing course?",
                "How long does the Digital Marketing course last?",
                "Duration of Digital Marketing course?",
                "What is the timeframe for Digital Marketing course?",
                "What is the duration of the Digital Marketing course?",
                "How long does the Digital Marketing course last?",
                "Can you tell me the duration of the Digital Marketing course?",
                "What is the timeframe for completing the Digital Marketing course?",
                "How many months does the Digital Marketing course take?",
                "What is the length of the Digital Marketing course?"

            ],
            "responses": [
                "The Digital Marketing course at Codeme Hub is 3 months long, providing comprehensive training in various digital marketing strategies.For more details, visit [Digital Marketing course](https://codemehub.com/digital-marketing-institute-in-calicut-kerala/).",
                "At Codeme Hub, the Digital Marketing course typically takes 3 months to complete, covering a wide range of digital marketing techniques.For more details, visit [Digital Marketing course](https://codemehub.com/digital-marketing-institute-in-calicut-kerala/).",
                "You can expect the Digital Marketing course at Codeme Hub to last approximately 3 months, focusing on practical skills and strategies in digital marketing.Find out more on our [Digital Marketing course](https://codemehub.com/digital-marketing-institute-in-calicut-kerala/).",
                "The duration of the Digital Marketing course at Codeme Hub is generally about 3 months, offering thorough training in digital marketing tools and techniques.For more details, visit [Digital Marketing course](https://codemehub.com/digital-marketing-institute-in-calicut-kerala/).",
                "Codeme Hub offers a Digital Marketing course designed to be completed in 3 months, emphasizing both theoretical knowledge and practical application in digital marketing.Find out more on our [Digital Marketing course](https://codemehub.com/digital-marketing-institute-in-calicut-kerala/)."
            ],
            "context": [""]
        },
        {
            "tag": "ui_ux_design_course_duration",
            "patterns": [
                "How much time is required to finish the UI/UX Design course?",
                "What is the duration of the UI/UX Design course?",
                "How long does the UI/UX Design course take?",
                "Duration of UI/UX Design course?",
                "What is the timeframe for UI/UX Design course?",
                "What is the duration of the UI/UX Design course?",
                "Can you tell me how long the UI/UX Design course takes to complete?",
                "How many months does the UI/UX Design course at Codeme Hub last?",
                "What is the timeframe for completing the UI/UX Design course?",
                "How long does it typically take to finish the UI/UX Design course?"
        
                    ],
            "responses": [
                "The UI/UX Design course is structured to be completed in 4 months, including practical design projects and user testing.For more information, visit [UI/UX Design course](https://codemehub.com/ui-ux-design-course-in-calicut-kerala/).",
                "At Codeme Hub, the UI/UX Design course typically takes 4 months to complete, focusing on both theoretical principles and practical applications in user interface and experience design.Check out our website for detailed information: [UI/UX Design course](https://codemehub.com/ui-ux-design-course-in-calicut-kerala/).",
                "You can expect the UI/UX Design course at Codeme Hub to last approximately 4 months, covering user interface design, user experience principles, and practical design projects.For more information, visit [UI/UX Design course](https://codemehub.com/ui-ux-design-course-in-calicut-kerala/).",
                "The duration of the UI/UX Design course at Codeme Hub is generally about 4 months, providing comprehensive training in creating intuitive and visually appealing interfaces.Check out our website for detailed information: [UI/UX Design course](https://codemehub.com/ui-ux-design-course-in-calicut-kerala/).",
                "Codeme Hub offers a UI/UX Design course designed to be completed in 4 months, emphasizing hands-on experience with user research, wireframing, prototyping, and usability testing.For more information, visit [UI/UX Design course](https://codemehub.com/ui-ux-design-course-in-calicut-kerala/)."
            ],
            "context": [""]
        }

        


    ]
}

    